ml_project/__init__.py
ml_project/pipelines/__init__.py
ml_project/pipelines/predict_pipeline.py
ml_project/pipelines/predict_pipeline_params.py
ml_project/pipelines/train_pipeline.py
ml_project/pipelines/train_pipeline_params.py
ml_project/pipelines/utils.py
ml_project/pipelines/configs/__init__.py
ml_project/pipelines/configs/default_predict_pipeline.yaml
ml_project/pipelines/configs/default_train_pipeline.yaml
ml_project/pipelines/configs/features/default.yaml
ml_project/pipelines/configs/features/short.yaml
ml_project/pipelines/configs/model/logistic.yaml
ml_project/pipelines/configs/model/random_forest.yaml
ml_project/pipelines/configs/preprocessing/identity_transformer.yaml
ml_project/pipelines/configs/preprocessing/one_hot_transformer.yaml
ml_project/pipelines/configs/split/default.yaml
ml_project/pipelines/configs/split/large_test.yaml
ml_project/pipelines/configs/train_pipelines/forest_train_pipeline.yaml
ml_project/pipelines/data/__init__.py
ml_project/pipelines/data/features_params.py
ml_project/pipelines/data/make_dataset.py
ml_project/pipelines/data/split_params.py
ml_project/pipelines/models/__init__.py
ml_project/pipelines/models/model_params.py
ml_project/pipelines/models/predict_model.py
ml_project/pipelines/models/train_model.py
ml_project/pipelines/preprocessing/__init__.py
ml_project/pipelines/preprocessing/preprocessing_params.py
ml_project/pipelines/preprocessing/transformers.py
ml_project/tests/__init__.py
ml_project/tests/test_data_module.py
ml_project/tests/test_models_module.py
ml_project/tests/test_predict_pipeline.py
ml_project/tests/test_preprocessing_module.py
ml_project/tests/test_train_pipeline.py
ml_project/tests/utils.py
pipelines/__init__.py
pipelines/predict_pipeline.py
pipelines/predict_pipeline_params.py
pipelines/train_pipeline.py
pipelines/train_pipeline_params.py
pipelines/utils.py
pipelines/configs/__init__.py
pipelines/configs/default_predict_pipeline.yaml
pipelines/configs/default_train_pipeline.yaml
ml_in_prod_juliarty_ml_project_1-0.2.0.dist-info/LICENSE
ml_in_prod_juliarty_ml_project_1-0.2.0.dist-info/METADATA
ml_in_prod_juliarty_ml_project_1-0.2.0.dist-info/WHEEL
ml_in_prod_juliarty_ml_project_1-0.2.0.dist-info/top_level.txt
ml_in_prod_juliarty_ml_project_1-0.2.0.dist-info/RECORD
