Metadata-Version: 2.1
Name: ml-in-prod-juliarty-ml-project-1
Version: 0.2.0
Summary: That is a homework project
Home-page: https://github.com/made-ml-in-prod-2022/juliarty
Author: Juliarty
Author-email: sirrzk.09@yandex.ru
Project-URL: Bug Reports, https://github.com/made-ml-in-prod-2022/juliarty/issues
Project-URL: Source, https://github.com/made-ml-in-prod-2022/juliarty/
Keywords: homework ml in prod
Requires-Python: >=3.8, <4
License-File: LICENSE
Requires-Dist: pyyaml (==6.0)
Requires-Dist: marshmallow-dataclass (==8.5.8)
Requires-Dist: pandas (~=1.4.2)
Requires-Dist: scikit-learn (~=1.0.2)
Requires-Dist: numpy (~=1.22.3)
Requires-Dist: omegaconf (~=2.1.2)
Requires-Dist: hydra-core (==1.1.2)
Requires-Dist: hydra-colorlog (==1.1.0)
Requires-Dist: pytest (~=7.1.2)
Requires-Dist: gdown (==4.4.0)
